local_ip_finder/__init__.py
local_ip_finder-0.0.1.dist-info/METADATA
local_ip_finder-0.0.1.dist-info/WHEEL
local_ip_finder-0.0.1.dist-info/top_level.txt
local_ip_finder-0.0.1.dist-info/RECORD
